[{"collectionName":"MetadataInstances","json":"{\"id\":\"69549862aedd5fe4733b3966\",\"lastUpdBy\":\"62bc5008d4958d013d97c7a6\",\"createUser\":\"admin@admin.com\",\"ancestorsName\":\"FDM\",\"hasPrimaryKey\":false,\"source\":{\"id\":\"695497a235a6fa1717313957\",\"_id\":\"695497a235a6fa1717313957\",\"user_id\":\"62bc5008d4958d013d97c7a6\",\"lastUpdBy\":\"62bc5008d4958d013d97c7a6\",\"createUser\":\"admin@admin.com\",\"name\":\"FDM\",\"connection_type\":\"source_and_target\",\"database_type\":\"MongoDB\",\"retry\":0,\"everLoadSchema\":true,\"schemaVersion\":\"f148f4b5-f542-48eb-b2e1-10efc97c9e50\",\"status\":\"ready\",\"tableCount\":0,\"testTime\":1768803955913,\"database_uri\":\"mongodb://null/null\",\"plain_password\":\"\",\"project\":\"\",\"transformed\":true,\"db_version\":\"8.0.9\",\"loadCount\":0,\"loadFieldsStatus\":\"loading\",\"submit\":true,\"loadSchemaField\":true,\"loadFieldErrMsg\":\"\",\"kafkaIgnoreInvalidRecord\":false,\"kafkaAcks\":\"-1\",\"kafkaCompressionType\":\"\",\"kafkaIgnorePushError\":false,\"agentTags\":[]},\"hasUnionIndex\":false,\"username\":\"admin@admin.com\",\"lastUpdate\":1768803955937,\"sourceType\":\"SOURCE\",\"hasTransformEx\":false,\"hasUpdateField\":false,\"createTime\":1768803676019,\"last_updated\":1768803956049,\"user_id\":\"62bc5008d4958d013d97c7a6\",\"qualified_name\":\"CONN_mongodb_io_tapdata_1_0-SNAPSHOT_695497a235a6fa1717313957\",\"meta_type\":\"database\",\"is_deleted\":false,\"original_name\":\"FDM\",\"dev_version\":1,\"last_user_name\":\"admin@admin.com\"}"},{"collectionName":"Connections","json":"{\"id\":\"695497a235a6fa1717313957\",\"name\":\"FDM\",\"config\":{\"mongodbLoadSchemaSampleSize\":1000,\"__connectionType\":\"source_and_target\",\"uri\":\"\",\"ssl\":false,\"schemaLimit\":1024,\"isUri\":true,\"id\":\"695497a235a6fa1717313957\"},\"connection_type\":\"source_and_target\",\"database_type\":\"MongoDB\",\"definitionScope\":\"public\",\"definitionVersion\":\"1.0-SNAPSHOT\",\"definitionGroup\":\"io.tapdata\",\"definitionPdkId\":\"mongodb\",\"definitionBuildNumber\":\"null\",\"definitionTags\":[\"schema-free\",\"Database\",\"doubleActive\"],\"definitionPdkAPIVersion\":\"2.0.5-SNAPSHOT\",\"pdkType\":\"pdk\",\"pdkHash\":\"4335aaa005ec1a74a4e2166bded2962e939ad50239f48b023b884f35b54129a5\",\"capabilities\":[{\"type\":20,\"id\":\"source_incremental_update_event_have_before\"},{\"type\":11,\"id\":\"execute_command_function\"},{\"type\":11,\"id\":\"batch_read_function\"},{\"type\":11,\"id\":\"stream_read_function\"},{\"type\":11,\"id\":\"batch_count_function\"},{\"type\":11,\"id\":\"timestamp_to_stream_offset_function\"},{\"type\":11,\"id\":\"write_record_function\"},{\"type\":11,\"id\":\"query_by_advance_filter_function\"},{\"type\":11,\"id\":\"create_table_v2_function\"},{\"type\":11,\"id\":\"drop_table_function\"},{\"type\":11,\"id\":\"create_index_function\"},{\"type\":11,\"id\":\"query_indexes_function\"},{\"type\":11,\"id\":\"count_by_partition_filter_function\"},{\"type\":11,\"id\":\"get_read_partitions_function\"},{\"type\":11,\"id\":\"query_field_min_max_value_function\"},{\"type\":11,\"id\":\"transaction_begin_function\"},{\"type\":11,\"id\":\"transaction_commit_function\"},{\"type\":11,\"id\":\"transaction_rollback_function\"},{\"type\":11,\"id\":\"get_table_info_function\"},{\"type\":11,\"id\":\"get_table_names_function\"},{\"type\":11,\"id\":\"error_handle_function\"},{\"type\":20,\"id\":\"master_slave_merge\"},{\"type\":20,\"id\":\"dynamic_schema\"},{\"type\":20,\"id\":\"dml_insert_policy\",\"alternatives\":[\"update_on_exists\",\"ignore_on_exists\",\"just_insert\"]},{\"type\":20,\"id\":\"dml_update_policy\",\"alternatives\":[\"ignore_on_nonexists\",\"insert_on_nonexists\",\"log_on_nonexists\"]},{\"type\":20,\"id\":\"api_server_supported\"},{\"type\":20,\"id\":\"source_support_exactly_once\"}],\"retry\":0,\"everLoadSchema\":true,\"schemaVersion\":\"f148f4b5-f542-48eb-b2e1-10efc97c9e50\",\"status\":\"ready\",\"lastStatus\":\"ready\",\"tableCount\":0,\"testTime\":1768803955913,\"database_uri\":\"mongodb://null/null\",\"plain_password\":\"\",\"loadAllTables\":true,\"openTableExcludeFilter\":false,\"project\":\"\",\"transformed\":true,\"db_version\":\"8.0.9\",\"schema\":{},\"loadCount\":0,\"loadFieldsStatus\":\"finished\",\"submit\":true,\"loadSchemaField\":true,\"lastUpdate\":1768803955937,\"loadFieldErrMsg\":\"\",\"kafkaConsumerRequestTimeout\":0,\"kafkaConsumerUseTransactional\":false,\"kafkaMaxPollRecords\":0,\"kafkaPollTimeoutMS\":0,\"kafkaMaxFetchBytes\":0,\"kafkaMaxFetchWaitMS\":0,\"kafkaIgnoreInvalidRecord\":false,\"kafkaProducerRequestTimeout\":0,\"kafkaProducerUseTransactional\":false,\"kafkaRetries\":0,\"kafkaBatchSize\":0,\"kafkaAcks\":\"-1\",\"kafkaLingerMS\":0,\"kafkaDeliveryTimeoutMS\":0,\"kafkaMaxRequestSize\":0,\"kafkaMaxBlockMS\":0,\"kafkaBufferMemory\":0,\"kafkaCompressionType\":\"\",\"kafkaPartitionKey\":\"\",\"kafkaIgnorePushError\":false,\"agentTags\":[],\"shareCdcEnable\":false,\"accessNodeType\":\"AUTOMATIC_PLATFORM_ALLOCATION\",\"accessNodeProcessId\":\"\",\"accessNodeProcessIdList\":[],\"accessNodeTypeEmpty\":false,\"shareCDCExternalStorageId\":\"\",\"loadSchemaTime\":1768413673546,\"schemaUpdateHour\":\"default\",\"heartbeatEnable\":false,\"isInit\":false,\"alarmInfo\":\"DataSourceConnectionDto{name='FDM', connection_type='source_and_target', retry=0, status='ready', tableCount=0, loadAllTables=true, loadFieldsStatus=finished, loadFieldErrMsg=}\",\"createTime\":1768803675243,\"last_updated\":1768803675243}"},{"collectionName":"MetadataInstances","json":"{\"id\":\"69670b382902e61eb53c4866\",\"lastUpdBy\":\"62bc5008d4958d013d97c7a6\",\"createUser\":\"admin@admin.com\",\"ancestorsName\":\"HKPMI\",\"hasPrimaryKey\":false,\"source\":{\"id\":\"69670b2b6353a88e827b68f8\",\"_id\":\"69670b2b6353a88e827b68f8\",\"user_id\":\"62bc5008d4958d013d97c7a6\",\"lastUpdBy\":\"62bc5008d4958d013d97c7a6\",\"createUser\":\"admin@admin.com\",\"name\":\"HKPMI\",\"connection_type\":\"source_and_target\",\"database_type\":\"PostgreSQL\",\"retry\":0,\"everLoadSchema\":true,\"schemaVersion\":\"71837f5c-cbec-45c0-87dc-06c98ce31201\",\"status\":\"ready\",\"tableCount\":110,\"testTime\":1768803952886,\"plain_password\":\"\",\"project\":\"\",\"transformed\":true,\"loadCount\":110,\"loadFieldsStatus\":\"finished\",\"submit\":true,\"loadSchemaField\":true,\"loadFieldErrMsg\":\"\",\"kafkaIgnoreInvalidRecord\":false,\"kafkaAcks\":\"-1\",\"kafkaCompressionType\":\"\",\"kafkaIgnorePushError\":false,\"agentTags\":[]},\"hasUnionIndex\":false,\"username\":\"admin@admin.com\",\"lastUpdate\":1768803952953,\"sourceType\":\"SOURCE\",\"hasTransformEx\":false,\"hasUpdateField\":false,\"createTime\":1768803675929,\"last_updated\":1768803954601,\"user_id\":\"62bc5008d4958d013d97c7a6\",\"qualified_name\":\"CONN_postgres_io_tapdata_1_0-SNAPSHOT_69670b2b6353a88e827b68f8\",\"meta_type\":\"database\",\"is_deleted\":false,\"original_name\":\"HKPMI\",\"dev_version\":1,\"last_user_name\":\"admin@admin.com\"}"},{"collectionName":"Connections","json":"{\"id\":\"69670b2b6353a88e827b68f8\",\"name\":\"HKPMI\",\"config\":{\"deploymentMode\":\"standalone\",\"port\":25432,\"logPluginName\":\"pgoutput\",\"pgtoHost\":\"127.0.0.1\",\"pgtoPort\":9876,\"partPublication\":false,\"globalPublicationName\":\"dbz_publication\",\"timezone\":\"\",\"allowReplication\":true,\"defaultWalLogSize\":102400,\"host\":\"\",\"database\":\"\",\"schema\":\"\",\"user\":\"\",\"__connectionType\":\"source_and_target\",\"id\":\"69670b2b6353a88e827b68f8\",\"datasourceInstanceId\":\"6179f0ff1833ab84a39c6cf183aa86c7\",\"password\":\"\"},\"connection_type\":\"source_and_target\",\"database_type\":\"PostgreSQL\",\"definitionScope\":\"public\",\"definitionVersion\":\"1.0-SNAPSHOT\",\"definitionGroup\":\"io.tapdata\",\"definitionPdkId\":\"postgres\",\"definitionBuildNumber\":\"null\",\"definitionTags\":[\"Database\",\"ssl\",\"doubleActive\",\"disableForeignKey\",\"NullsLast\"],\"definitionPdkAPIVersion\":\"2.0.5-SNAPSHOT\",\"pdkType\":\"pdk\",\"pdkHash\":\"8dea069f269dd428d82e60e75d0d91b6dc61be7be26eae7bc407d7b95d3b0594\",\"capabilities\":[{\"type\":11,\"id\":\"count_raw_command_function\"},{\"type\":11,\"id\":\"run_raw_command_function\"},{\"type\":11,\"id\":\"execute_command_function\"},{\"type\":11,\"id\":\"release_external_function\"},{\"type\":11,\"id\":\"batch_read_function\"},{\"type\":11,\"id\":\"stream_read_function\"},{\"type\":11,\"id\":\"batch_count_function\"},{\"type\":11,\"id\":\"timestamp_to_stream_offset_function\"},{\"type\":11,\"id\":\"write_record_function\"},{\"type\":11,\"id\":\"after_initial_sync_function\"},{\"type\":11,\"id\":\"query_by_filter_function\"},{\"type\":11,\"id\":\"query_by_advance_filter_function\"},{\"type\":11,\"id\":\"create_table_v2_function\"},{\"type\":11,\"id\":\"clear_table_function\"},{\"type\":11,\"id\":\"drop_table_function\"},{\"type\":11,\"id\":\"create_index_function\"},{\"type\":11,\"id\":\"delete_index_function\"},{\"type\":11,\"id\":\"query_indexes_function\"},{\"type\":11,\"id\":\"query_constraints_function\"},{\"type\":11,\"id\":\"create_constraint_function\"},{\"type\":11,\"id\":\"drop_constraint_function\"},{\"type\":11,\"id\":\"alter_field_attributes_function\"},{\"type\":11,\"id\":\"alter_field_name_function\"},{\"type\":11,\"id\":\"drop_field_function\"},{\"type\":11,\"id\":\"new_field_function\"},{\"type\":11,\"id\":\"count_by_partition_filter_function\"},{\"type\":11,\"id\":\"stream_read_multi_connection_function\"},{\"type\":11,\"id\":\"transaction_begin_function\"},{\"type\":11,\"id\":\"transaction_commit_function\"},{\"type\":11,\"id\":\"transaction_rollback_function\"},{\"type\":11,\"id\":\"query_hash_by_advance_filter_function\"},{\"type\":11,\"id\":\"get_stream_offset_function\"},{\"type\":11,\"id\":\"export_event_sql_function\"},{\"type\":11,\"id\":\"flush_offset_function\"},{\"type\":11,\"id\":\"get_table_info_function\"},{\"type\":11,\"id\":\"get_table_names_function\"},{\"type\":11,\"id\":\"error_handle_function\"},{\"type\":11,\"id\":\"execute_command_v2_function\"},{\"type\":20,\"id\":\"dml_insert_policy\",\"alternatives\":[\"update_on_exists\",\"ignore_on_exists\",\"just_insert\"]},{\"type\":20,\"id\":\"dml_update_policy\",\"alternatives\":[\"ignore_on_nonexists\",\"insert_on_nonexists\",\"log_on_nonexists\"]},{\"type\":20,\"id\":\"dml_delete_policy\",\"alternatives\":[\"ignore_on_nonexists\",\"log_on_nonexists\"]},{\"type\":20,\"id\":\"dml_check_policy\",\"alternatives\":[\"ignore_all_check\",\"default_check\"]},{\"type\":20,\"id\":\"api_server_supported\"},{\"type\":20,\"id\":\"source_support_exactly_once\"},{\"type\":20,\"id\":\"batch_read_hash_split\"},{\"type\":20,\"id\":\"source_support_partition\"}],\"retry\":0,\"everLoadSchema\":true,\"schemaVersion\":\"71837f5c-cbec-45c0-87dc-06c98ce31201\",\"status\":\"ready\",\"lastStatus\":\"ready\",\"tableCount\":110,\"testTime\":1768803952886,\"dataSourceMonitor\":false,\"plain_password\":\"\",\"loadAllTables\":true,\"openTableExcludeFilter\":false,\"project\":\"\",\"transformed\":true,\"schema\":{},\"loadCount\":110,\"loadFieldsStatus\":\"finished\",\"submit\":true,\"loadSchemaField\":true,\"lastUpdate\":1768803952953,\"loadFieldErrMsg\":\"\",\"kafkaConsumerRequestTimeout\":0,\"kafkaConsumerUseTransactional\":false,\"kafkaMaxPollRecords\":0,\"kafkaPollTimeoutMS\":0,\"kafkaMaxFetchBytes\":0,\"kafkaMaxFetchWaitMS\":0,\"kafkaIgnoreInvalidRecord\":false,\"kafkaProducerRequestTimeout\":0,\"kafkaProducerUseTransactional\":false,\"kafkaRetries\":0,\"kafkaBatchSize\":0,\"kafkaAcks\":\"-1\",\"kafkaLingerMS\":0,\"kafkaDeliveryTimeoutMS\":0,\"kafkaMaxRequestSize\":0,\"kafkaMaxBlockMS\":0,\"kafkaBufferMemory\":0,\"kafkaCompressionType\":\"\",\"kafkaPartitionKey\":\"\",\"kafkaIgnorePushError\":false,\"agentTags\":[],\"shareCdcEnable\":true,\"accessNodeType\":\"AUTOMATIC_PLATFORM_ALLOCATION\",\"accessNodeProcessId\":\"\",\"accessNodeProcessIdList\":[],\"accessNodeTypeEmpty\":false,\"shareCDCExternalStorageId\":\"696dccf3c085cb3a6493261e\",\"loadSchemaTime\":1768803954564,\"schemaUpdateHour\":\"default\",\"heartbeatEnable\":false,\"multiConnectionInstanceId\":\"b3a358f75fd89cec750cc6012ebf6798\",\"namespace\":[\"hkpmi\"],\"datasourceInstanceTag\":\"192.168.1.184:25432\",\"isInit\":false,\"alarmInfo\":\"DataSourceConnectionDto{name='HKPMI', connection_type='source_and_target', retry=0, status='ready', tableCount=110, loadAllTables=true, loadFieldsStatus=finished, loadFieldErrMsg=}\",\"createTime\":1768803675352,\"last_updated\":1768803675352}"},{"collectionName":"MetadataInstances","json":"{\"id\":\"6967134f2902e61eb5518f39\",\"lastUpdBy\":\"62bc5008d4958d013d97c7a6\",\"createUser\":\"admin@admin.com\",\"ancestorsName\":\"HPI\",\"hasPrimaryKey\":false,\"source\":{\"id\":\"6967134e35bb3bfc3cf38f9c\",\"_id\":\"6967134e35bb3bfc3cf38f9c\",\"user_id\":\"62bc5008d4958d013d97c7a6\",\"lastUpdBy\":\"62bc5008d4958d013d97c7a6\",\"createUser\":\"admin@admin.com\",\"name\":\"HPI\",\"connection_type\":\"source_and_target\",\"database_type\":\"PostgreSQL\",\"retry\":0,\"everLoadSchema\":true,\"schemaVersion\":\"9193147d-6492-410a-bc6b-bed1bb1fa010\",\"status\":\"ready\",\"tableCount\":3,\"testTime\":1768803953956,\"plain_password\":\"\",\"project\":\"\",\"transformed\":true,\"loadCount\":3,\"loadFieldsStatus\":\"finished\",\"submit\":true,\"loadSchemaField\":true,\"loadFieldErrMsg\":\"\",\"kafkaIgnoreInvalidRecord\":false,\"kafkaAcks\":\"-1\",\"kafkaCompressionType\":\"\",\"kafkaIgnorePushError\":false,\"agentTags\":[]},\"hasUnionIndex\":false,\"username\":\"admin@admin.com\",\"lastUpdate\":1768803954014,\"sourceType\":\"SOURCE\",\"hasTransformEx\":false,\"hasUpdateField\":false,\"createTime\":1768803676009,\"last_updated\":1768803954474,\"user_id\":\"62bc5008d4958d013d97c7a6\",\"qualified_name\":\"CONN_postgres_io_tapdata_1_0-SNAPSHOT_6967134e35bb3bfc3cf38f9c\",\"meta_type\":\"database\",\"is_deleted\":false,\"original_name\":\"HPI\",\"dev_version\":1,\"last_user_name\":\"admin@admin.com\"}"},{"collectionName":"Connections","json":"{\"id\":\"6967134e35bb3bfc3cf38f9c\",\"name\":\"HPI\",\"config\":{\"deploymentMode\":\"standalone\",\"port\":25432,\"logPluginName\":\"pgoutput\",\"pgtoHost\":\"127.0.0.1\",\"pgtoPort\":9876,\"partPublication\":false,\"globalPublicationName\":\"dbz_publication\",\"timezone\":\"\",\"allowReplication\":true,\"defaultWalLogSize\":102400,\"host\":\"\",\"database\":\"\",\"schema\":\"\",\"user\":\"\",\"__connectionType\":\"source_and_target\",\"id\":\"6967134e35bb3bfc3cf38f9c\",\"datasourceInstanceId\":\"6179f0ff1833ab84a39c6cf183aa86c7\",\"password\":\"\"},\"connection_type\":\"source_and_target\",\"database_type\":\"PostgreSQL\",\"definitionScope\":\"public\",\"definitionVersion\":\"1.0-SNAPSHOT\",\"definitionGroup\":\"io.tapdata\",\"definitionPdkId\":\"postgres\",\"definitionBuildNumber\":\"null\",\"definitionTags\":[\"Database\",\"ssl\",\"doubleActive\",\"disableForeignKey\",\"NullsLast\"],\"definitionPdkAPIVersion\":\"2.0.5-SNAPSHOT\",\"pdkType\":\"pdk\",\"pdkHash\":\"8dea069f269dd428d82e60e75d0d91b6dc61be7be26eae7bc407d7b95d3b0594\",\"capabilities\":[{\"type\":11,\"id\":\"count_raw_command_function\"},{\"type\":11,\"id\":\"run_raw_command_function\"},{\"type\":11,\"id\":\"execute_command_function\"},{\"type\":11,\"id\":\"release_external_function\"},{\"type\":11,\"id\":\"batch_read_function\"},{\"type\":11,\"id\":\"stream_read_function\"},{\"type\":11,\"id\":\"batch_count_function\"},{\"type\":11,\"id\":\"timestamp_to_stream_offset_function\"},{\"type\":11,\"id\":\"write_record_function\"},{\"type\":11,\"id\":\"after_initial_sync_function\"},{\"type\":11,\"id\":\"query_by_filter_function\"},{\"type\":11,\"id\":\"query_by_advance_filter_function\"},{\"type\":11,\"id\":\"create_table_v2_function\"},{\"type\":11,\"id\":\"clear_table_function\"},{\"type\":11,\"id\":\"drop_table_function\"},{\"type\":11,\"id\":\"create_index_function\"},{\"type\":11,\"id\":\"delete_index_function\"},{\"type\":11,\"id\":\"query_indexes_function\"},{\"type\":11,\"id\":\"query_constraints_function\"},{\"type\":11,\"id\":\"create_constraint_function\"},{\"type\":11,\"id\":\"drop_constraint_function\"},{\"type\":11,\"id\":\"alter_field_attributes_function\"},{\"type\":11,\"id\":\"alter_field_name_function\"},{\"type\":11,\"id\":\"drop_field_function\"},{\"type\":11,\"id\":\"new_field_function\"},{\"type\":11,\"id\":\"count_by_partition_filter_function\"},{\"type\":11,\"id\":\"stream_read_multi_connection_function\"},{\"type\":11,\"id\":\"transaction_begin_function\"},{\"type\":11,\"id\":\"transaction_commit_function\"},{\"type\":11,\"id\":\"transaction_rollback_function\"},{\"type\":11,\"id\":\"query_hash_by_advance_filter_function\"},{\"type\":11,\"id\":\"get_stream_offset_function\"},{\"type\":11,\"id\":\"export_event_sql_function\"},{\"type\":11,\"id\":\"flush_offset_function\"},{\"type\":11,\"id\":\"get_table_info_function\"},{\"type\":11,\"id\":\"get_table_names_function\"},{\"type\":11,\"id\":\"error_handle_function\"},{\"type\":11,\"id\":\"execute_command_v2_function\"},{\"type\":20,\"id\":\"dml_insert_policy\",\"alternatives\":[\"update_on_exists\",\"ignore_on_exists\",\"just_insert\"]},{\"type\":20,\"id\":\"dml_update_policy\",\"alternatives\":[\"ignore_on_nonexists\",\"insert_on_nonexists\",\"log_on_nonexists\"]},{\"type\":20,\"id\":\"dml_delete_policy\",\"alternatives\":[\"ignore_on_nonexists\",\"log_on_nonexists\"]},{\"type\":20,\"id\":\"dml_check_policy\",\"alternatives\":[\"ignore_all_check\",\"default_check\"]},{\"type\":20,\"id\":\"api_server_supported\"},{\"type\":20,\"id\":\"source_support_exactly_once\"},{\"type\":20,\"id\":\"batch_read_hash_split\"},{\"type\":20,\"id\":\"source_support_partition\"}],\"retry\":0,\"everLoadSchema\":true,\"schemaVersion\":\"9193147d-6492-410a-bc6b-bed1bb1fa010\",\"status\":\"ready\",\"lastStatus\":\"ready\",\"tableCount\":3,\"testTime\":1768803953956,\"dataSourceMonitor\":false,\"plain_password\":\"\",\"loadAllTables\":true,\"openTableExcludeFilter\":false,\"project\":\"\",\"transformed\":true,\"schema\":{},\"loadCount\":3,\"loadFieldsStatus\":\"finished\",\"submit\":true,\"loadSchemaField\":true,\"lastUpdate\":1768803954014,\"loadFieldErrMsg\":\"\",\"kafkaConsumerRequestTimeout\":0,\"kafkaConsumerUseTransactional\":false,\"kafkaMaxPollRecords\":0,\"kafkaPollTimeoutMS\":0,\"kafkaMaxFetchBytes\":0,\"kafkaMaxFetchWaitMS\":0,\"kafkaIgnoreInvalidRecord\":false,\"kafkaProducerRequestTimeout\":0,\"kafkaProducerUseTransactional\":false,\"kafkaRetries\":0,\"kafkaBatchSize\":0,\"kafkaAcks\":\"-1\",\"kafkaLingerMS\":0,\"kafkaDeliveryTimeoutMS\":0,\"kafkaMaxRequestSize\":0,\"kafkaMaxBlockMS\":0,\"kafkaBufferMemory\":0,\"kafkaCompressionType\":\"\",\"kafkaPartitionKey\":\"\",\"kafkaIgnorePushError\":false,\"agentTags\":[],\"shareCdcEnable\":true,\"accessNodeType\":\"AUTOMATIC_PLATFORM_ALLOCATION\",\"accessNodeProcessId\":\"\",\"accessNodeProcessIdList\":[],\"accessNodeTypeEmpty\":false,\"shareCDCExternalStorageId\":\"696dccf3c085cb3a6493261e\",\"loadSchemaTime\":1768803954452,\"schemaUpdateHour\":\"default\",\"heartbeatEnable\":false,\"multiConnectionInstanceId\":\"b3a358f75fd89cec750cc6012ebf6798\",\"namespace\":[\"hpi\"],\"datasourceInstanceTag\":\"192.168.1.184:25432\",\"isInit\":false,\"alarmInfo\":\"DataSourceConnectionDto{name='HPI', connection_type='source_and_target', retry=0, status='ready', tableCount=3, loadAllTables=true, loadFieldsStatus=finished, loadFieldErrMsg=}\",\"createTime\":1768803675321,\"last_updated\":1768803675321}"},{"collectionName":"MetadataInstances","json":"{\"id\":\"6967136b2902e61eb551dc1e\",\"lastUpdBy\":\"62bc5008d4958d013d97c7a6\",\"createUser\":\"admin@admin.com\",\"ancestorsName\":\"CMS\",\"hasPrimaryKey\":false,\"source\":{\"id\":\"6967136b35bb3bfc3cf38fab\",\"_id\":\"6967136b35bb3bfc3cf38fab\",\"user_id\":\"62bc5008d4958d013d97c7a6\",\"lastUpdBy\":\"62bc5008d4958d013d97c7a6\",\"createUser\":\"admin@admin.com\",\"name\":\"CMS\",\"connection_type\":\"source_and_target\",\"database_type\":\"PostgreSQL\",\"retry\":0,\"everLoadSchema\":true,\"schemaVersion\":\"49601094-7c38-40b5-9314-5479450477c2\",\"status\":\"ready\",\"tableCount\":1,\"testTime\":1768803955763,\"plain_password\":\"\",\"project\":\"\",\"transformed\":true,\"loadCount\":1,\"loadFieldsStatus\":\"finished\",\"submit\":true,\"loadSchemaField\":true,\"loadFieldErrMsg\":\"\",\"kafkaIgnoreInvalidRecord\":false,\"kafkaAcks\":\"-1\",\"kafkaCompressionType\":\"\",\"kafkaIgnorePushError\":false,\"agentTags\":[]},\"hasUnionIndex\":false,\"username\":\"admin@admin.com\",\"lastUpdate\":1768803955805,\"sourceType\":\"SOURCE\",\"hasTransformEx\":false,\"hasUpdateField\":false,\"createTime\":1768803675997,\"last_updated\":1768803956326,\"user_id\":\"62bc5008d4958d013d97c7a6\",\"qualified_name\":\"CONN_postgres_io_tapdata_1_0-SNAPSHOT_6967136b35bb3bfc3cf38fab\",\"meta_type\":\"database\",\"is_deleted\":false,\"original_name\":\"CMS\",\"dev_version\":1,\"last_user_name\":\"admin@admin.com\"}"},{"collectionName":"Connections","json":"{\"id\":\"6967136b35bb3bfc3cf38fab\",\"name\":\"CMS\",\"config\":{\"deploymentMode\":\"standalone\",\"port\":25432,\"logPluginName\":\"pgoutput\",\"pgtoHost\":\"127.0.0.1\",\"pgtoPort\":9876,\"partPublication\":false,\"globalPublicationName\":\"dbz_publication\",\"timezone\":\"\",\"allowReplication\":true,\"defaultWalLogSize\":102400,\"host\":\"\",\"database\":\"\",\"schema\":\"\",\"user\":\"\",\"__connectionType\":\"source_and_target\",\"id\":\"6967136b35bb3bfc3cf38fab\",\"datasourceInstanceId\":\"6179f0ff1833ab84a39c6cf183aa86c7\",\"password\":\"\"},\"connection_type\":\"source_and_target\",\"database_type\":\"PostgreSQL\",\"definitionScope\":\"public\",\"definitionVersion\":\"1.0-SNAPSHOT\",\"definitionGroup\":\"io.tapdata\",\"definitionPdkId\":\"postgres\",\"definitionBuildNumber\":\"null\",\"definitionTags\":[\"Database\",\"ssl\",\"doubleActive\",\"disableForeignKey\",\"NullsLast\"],\"definitionPdkAPIVersion\":\"2.0.5-SNAPSHOT\",\"pdkType\":\"pdk\",\"pdkHash\":\"8dea069f269dd428d82e60e75d0d91b6dc61be7be26eae7bc407d7b95d3b0594\",\"capabilities\":[{\"type\":11,\"id\":\"count_raw_command_function\"},{\"type\":11,\"id\":\"run_raw_command_function\"},{\"type\":11,\"id\":\"execute_command_function\"},{\"type\":11,\"id\":\"release_external_function\"},{\"type\":11,\"id\":\"batch_read_function\"},{\"type\":11,\"id\":\"stream_read_function\"},{\"type\":11,\"id\":\"batch_count_function\"},{\"type\":11,\"id\":\"timestamp_to_stream_offset_function\"},{\"type\":11,\"id\":\"write_record_function\"},{\"type\":11,\"id\":\"after_initial_sync_function\"},{\"type\":11,\"id\":\"query_by_filter_function\"},{\"type\":11,\"id\":\"query_by_advance_filter_function\"},{\"type\":11,\"id\":\"create_table_v2_function\"},{\"type\":11,\"id\":\"clear_table_function\"},{\"type\":11,\"id\":\"drop_table_function\"},{\"type\":11,\"id\":\"create_index_function\"},{\"type\":11,\"id\":\"delete_index_function\"},{\"type\":11,\"id\":\"query_indexes_function\"},{\"type\":11,\"id\":\"query_constraints_function\"},{\"type\":11,\"id\":\"create_constraint_function\"},{\"type\":11,\"id\":\"drop_constraint_function\"},{\"type\":11,\"id\":\"alter_field_attributes_function\"},{\"type\":11,\"id\":\"alter_field_name_function\"},{\"type\":11,\"id\":\"drop_field_function\"},{\"type\":11,\"id\":\"new_field_function\"},{\"type\":11,\"id\":\"count_by_partition_filter_function\"},{\"type\":11,\"id\":\"stream_read_multi_connection_function\"},{\"type\":11,\"id\":\"transaction_begin_function\"},{\"type\":11,\"id\":\"transaction_commit_function\"},{\"type\":11,\"id\":\"transaction_rollback_function\"},{\"type\":11,\"id\":\"query_hash_by_advance_filter_function\"},{\"type\":11,\"id\":\"get_stream_offset_function\"},{\"type\":11,\"id\":\"export_event_sql_function\"},{\"type\":11,\"id\":\"flush_offset_function\"},{\"type\":11,\"id\":\"get_table_info_function\"},{\"type\":11,\"id\":\"get_table_names_function\"},{\"type\":11,\"id\":\"error_handle_function\"},{\"type\":11,\"id\":\"execute_command_v2_function\"},{\"type\":20,\"id\":\"dml_insert_policy\",\"alternatives\":[\"update_on_exists\",\"ignore_on_exists\",\"just_insert\"]},{\"type\":20,\"id\":\"dml_update_policy\",\"alternatives\":[\"ignore_on_nonexists\",\"insert_on_nonexists\",\"log_on_nonexists\"]},{\"type\":20,\"id\":\"dml_delete_policy\",\"alternatives\":[\"ignore_on_nonexists\",\"log_on_nonexists\"]},{\"type\":20,\"id\":\"dml_check_policy\",\"alternatives\":[\"ignore_all_check\",\"default_check\"]},{\"type\":20,\"id\":\"api_server_supported\"},{\"type\":20,\"id\":\"source_support_exactly_once\"},{\"type\":20,\"id\":\"batch_read_hash_split\"},{\"type\":20,\"id\":\"source_support_partition\"}],\"retry\":0,\"everLoadSchema\":true,\"schemaVersion\":\"49601094-7c38-40b5-9314-5479450477c2\",\"status\":\"ready\",\"lastStatus\":\"ready\",\"tableCount\":1,\"testTime\":1768803955763,\"dataSourceMonitor\":false,\"plain_password\":\"\",\"loadAllTables\":true,\"openTableExcludeFilter\":false,\"project\":\"\",\"transformed\":true,\"schema\":{},\"loadCount\":1,\"loadFieldsStatus\":\"finished\",\"submit\":true,\"loadSchemaField\":true,\"lastUpdate\":1768803955805,\"loadFieldErrMsg\":\"\",\"kafkaConsumerRequestTimeout\":0,\"kafkaConsumerUseTransactional\":false,\"kafkaMaxPollRecords\":0,\"kafkaPollTimeoutMS\":0,\"kafkaMaxFetchBytes\":0,\"kafkaMaxFetchWaitMS\":0,\"kafkaIgnoreInvalidRecord\":false,\"kafkaProducerRequestTimeout\":0,\"kafkaProducerUseTransactional\":false,\"kafkaRetries\":0,\"kafkaBatchSize\":0,\"kafkaAcks\":\"-1\",\"kafkaLingerMS\":0,\"kafkaDeliveryTimeoutMS\":0,\"kafkaMaxRequestSize\":0,\"kafkaMaxBlockMS\":0,\"kafkaBufferMemory\":0,\"kafkaCompressionType\":\"\",\"kafkaPartitionKey\":\"\",\"kafkaIgnorePushError\":false,\"agentTags\":[],\"shareCdcEnable\":true,\"accessNodeType\":\"AUTOMATIC_PLATFORM_ALLOCATION\",\"accessNodeProcessId\":\"\",\"accessNodeProcessIdList\":[],\"accessNodeTypeEmpty\":false,\"shareCDCExternalStorageId\":\"696dccf3c085cb3a6493261e\",\"loadSchemaTime\":1768803956268,\"schemaUpdateHour\":\"default\",\"heartbeatEnable\":false,\"multiConnectionInstanceId\":\"b3a358f75fd89cec750cc6012ebf6798\",\"namespace\":[\"cms\"],\"datasourceInstanceTag\":\"192.168.1.184:25432\",\"isInit\":false,\"alarmInfo\":\"DataSourceConnectionDto{name='CMS', connection_type='source_and_target', retry=0, status='ready', tableCount=1, loadAllTables=true, loadFieldsStatus=finished, loadFieldErrMsg=}\",\"createTime\":1768803675288,\"last_updated\":1768803675288}"},{"collectionName":"MetadataInstances","json":"{\"id\":\"69549862aedd5fe4733b3966\",\"lastUpdBy\":\"62bc5008d4958d013d97c7a6\",\"createUser\":\"admin@admin.com\",\"ancestorsName\":\"FDM\",\"hasPrimaryKey\":false,\"source\":{\"id\":\"695497a235a6fa1717313957\",\"_id\":\"695497a235a6fa1717313957\",\"user_id\":\"62bc5008d4958d013d97c7a6\",\"lastUpdBy\":\"62bc5008d4958d013d97c7a6\",\"createUser\":\"admin@admin.com\",\"name\":\"FDM\",\"connection_type\":\"source_and_target\",\"database_type\":\"MongoDB\",\"retry\":0,\"everLoadSchema\":true,\"schemaVersion\":\"f148f4b5-f542-48eb-b2e1-10efc97c9e50\",\"status\":\"ready\",\"tableCount\":0,\"testTime\":1768803955913,\"database_uri\":\"mongodb://null/null\",\"plain_password\":\"\",\"project\":\"\",\"transformed\":true,\"db_version\":\"8.0.9\",\"loadCount\":0,\"loadFieldsStatus\":\"loading\",\"submit\":true,\"loadSchemaField\":true,\"loadFieldErrMsg\":\"\",\"kafkaIgnoreInvalidRecord\":false,\"kafkaAcks\":\"-1\",\"kafkaCompressionType\":\"\",\"kafkaIgnorePushError\":false,\"agentTags\":[]},\"hasUnionIndex\":false,\"username\":\"admin@admin.com\",\"lastUpdate\":1768803955937,\"sourceType\":\"SOURCE\",\"hasTransformEx\":false,\"hasUpdateField\":false,\"createTime\":1768803676019,\"last_updated\":1768803956049,\"user_id\":\"62bc5008d4958d013d97c7a6\",\"qualified_name\":\"CONN_mongodb_io_tapdata_1_0-SNAPSHOT_695497a235a6fa1717313957\",\"meta_type\":\"database\",\"is_deleted\":false,\"original_name\":\"FDM\",\"dev_version\":1,\"last_user_name\":\"admin@admin.com\"}"},{"collectionName":"Connections","json":"{\"id\":\"695497a235a6fa1717313957\",\"name\":\"FDM\",\"config\":{\"mongodbLoadSchemaSampleSize\":1000,\"__connectionType\":\"source_and_target\",\"uri\":\"\",\"ssl\":false,\"schemaLimit\":1024,\"isUri\":true,\"id\":\"695497a235a6fa1717313957\"},\"connection_type\":\"source_and_target\",\"database_type\":\"MongoDB\",\"definitionScope\":\"public\",\"definitionVersion\":\"1.0-SNAPSHOT\",\"definitionGroup\":\"io.tapdata\",\"definitionPdkId\":\"mongodb\",\"definitionBuildNumber\":\"null\",\"definitionTags\":[\"schema-free\",\"Database\",\"doubleActive\"],\"definitionPdkAPIVersion\":\"2.0.5-SNAPSHOT\",\"pdkType\":\"pdk\",\"pdkHash\":\"4335aaa005ec1a74a4e2166bded2962e939ad50239f48b023b884f35b54129a5\",\"capabilities\":[{\"type\":20,\"id\":\"source_incremental_update_event_have_before\"},{\"type\":11,\"id\":\"execute_command_function\"},{\"type\":11,\"id\":\"batch_read_function\"},{\"type\":11,\"id\":\"stream_read_function\"},{\"type\":11,\"id\":\"batch_count_function\"},{\"type\":11,\"id\":\"timestamp_to_stream_offset_function\"},{\"type\":11,\"id\":\"write_record_function\"},{\"type\":11,\"id\":\"query_by_advance_filter_function\"},{\"type\":11,\"id\":\"create_table_v2_function\"},{\"type\":11,\"id\":\"drop_table_function\"},{\"type\":11,\"id\":\"create_index_function\"},{\"type\":11,\"id\":\"query_indexes_function\"},{\"type\":11,\"id\":\"count_by_partition_filter_function\"},{\"type\":11,\"id\":\"get_read_partitions_function\"},{\"type\":11,\"id\":\"query_field_min_max_value_function\"},{\"type\":11,\"id\":\"transaction_begin_function\"},{\"type\":11,\"id\":\"transaction_commit_function\"},{\"type\":11,\"id\":\"transaction_rollback_function\"},{\"type\":11,\"id\":\"get_table_info_function\"},{\"type\":11,\"id\":\"get_table_names_function\"},{\"type\":11,\"id\":\"error_handle_function\"},{\"type\":20,\"id\":\"master_slave_merge\"},{\"type\":20,\"id\":\"dynamic_schema\"},{\"type\":20,\"id\":\"dml_insert_policy\",\"alternatives\":[\"update_on_exists\",\"ignore_on_exists\",\"just_insert\"]},{\"type\":20,\"id\":\"dml_update_policy\",\"alternatives\":[\"ignore_on_nonexists\",\"insert_on_nonexists\",\"log_on_nonexists\"]},{\"type\":20,\"id\":\"api_server_supported\"},{\"type\":20,\"id\":\"source_support_exactly_once\"}],\"retry\":0,\"everLoadSchema\":true,\"schemaVersion\":\"f148f4b5-f542-48eb-b2e1-10efc97c9e50\",\"status\":\"ready\",\"lastStatus\":\"ready\",\"tableCount\":0,\"testTime\":1768803955913,\"database_uri\":\"mongodb://null/null\",\"plain_password\":\"\",\"loadAllTables\":true,\"openTableExcludeFilter\":false,\"project\":\"\",\"transformed\":true,\"db_version\":\"8.0.9\",\"schema\":{},\"loadCount\":0,\"loadFieldsStatus\":\"finished\",\"submit\":true,\"loadSchemaField\":true,\"lastUpdate\":1768803955937,\"loadFieldErrMsg\":\"\",\"kafkaConsumerRequestTimeout\":0,\"kafkaConsumerUseTransactional\":false,\"kafkaMaxPollRecords\":0,\"kafkaPollTimeoutMS\":0,\"kafkaMaxFetchBytes\":0,\"kafkaMaxFetchWaitMS\":0,\"kafkaIgnoreInvalidRecord\":false,\"kafkaProducerRequestTimeout\":0,\"kafkaProducerUseTransactional\":false,\"kafkaRetries\":0,\"kafkaBatchSize\":0,\"kafkaAcks\":\"-1\",\"kafkaLingerMS\":0,\"kafkaDeliveryTimeoutMS\":0,\"kafkaMaxRequestSize\":0,\"kafkaMaxBlockMS\":0,\"kafkaBufferMemory\":0,\"kafkaCompressionType\":\"\",\"kafkaPartitionKey\":\"\",\"kafkaIgnorePushError\":false,\"agentTags\":[],\"shareCdcEnable\":false,\"accessNodeType\":\"AUTOMATIC_PLATFORM_ALLOCATION\",\"accessNodeProcessId\":\"\",\"accessNodeProcessIdList\":[],\"accessNodeTypeEmpty\":false,\"shareCDCExternalStorageId\":\"\",\"loadSchemaTime\":1768413673546,\"schemaUpdateHour\":\"default\",\"heartbeatEnable\":false,\"isInit\":false,\"alarmInfo\":\"DataSourceConnectionDto{name='FDM', connection_type='source_and_target', retry=0, status='ready', tableCount=0, loadAllTables=true, loadFieldsStatus=finished, loadFieldErrMsg=}\",\"createTime\":1768803675243,\"last_updated\":1768803675243}"},{"collectionName":"MetadataInstances","json":"{\"id\":\"69549865aedd5fe4733b3c1d\",\"lastUpdBy\":\"62bc5008d4958d013d97c7a6\",\"createUser\":\"admin@admin.com\",\"ancestorsName\":\"MDM\",\"hasPrimaryKey\":false,\"source\":{\"id\":\"695497a235a6fa171731395e\",\"_id\":\"695497a235a6fa171731395e\",\"user_id\":\"62bc5008d4958d013d97c7a6\",\"lastUpdBy\":\"62bc5008d4958d013d97c7a6\",\"createUser\":\"admin@admin.com\",\"name\":\"MDM\",\"connection_type\":\"source_and_target\",\"database_type\":\"MongoDB\",\"retry\":0,\"everLoadSchema\":true,\"schemaVersion\":\"4f0fa5ba-4c7d-454d-b15b-e034d6556086\",\"status\":\"ready\",\"tableCount\":2,\"testTime\":1768890124835,\"database_uri\":\"mongodb://null/null\",\"plain_password\":\"\",\"project\":\"\",\"transformed\":true,\"db_version\":\"8.0.9\",\"loadCount\":2,\"loadFieldsStatus\":\"finished\",\"submit\":true,\"loadSchemaField\":true,\"loadFieldErrMsg\":\"\",\"kafkaIgnoreInvalidRecord\":false,\"kafkaAcks\":\"-1\",\"kafkaCompressionType\":\"\",\"kafkaIgnorePushError\":false,\"agentTags\":[]},\"hasUnionIndex\":false,\"username\":\"admin@admin.com\",\"lastUpdate\":1768890124874,\"sourceType\":\"SOURCE\",\"hasTransformEx\":false,\"hasUpdateField\":false,\"createTime\":1768803675966,\"last_updated\":1768890125278,\"user_id\":\"62bc5008d4958d013d97c7a6\",\"qualified_name\":\"CONN_mongodb_io_tapdata_1_0-SNAPSHOT_695497a235a6fa171731395e\",\"meta_type\":\"database\",\"is_deleted\":false,\"original_name\":\"MDM\",\"dev_version\":1,\"last_user_name\":\"admin@admin.com\"}"},{"collectionName":"Connections","json":"{\"id\":\"695497a235a6fa171731395e\",\"name\":\"MDM\",\"config\":{\"mongodbLoadSchemaSampleSize\":1000,\"__connectionType\":\"source_and_target\",\"uri\":\"\",\"ssl\":false,\"schemaLimit\":1024,\"isUri\":true,\"id\":\"695497a235a6fa171731395e\"},\"connection_type\":\"source_and_target\",\"database_type\":\"MongoDB\",\"definitionScope\":\"public\",\"definitionVersion\":\"1.0-SNAPSHOT\",\"definitionGroup\":\"io.tapdata\",\"definitionPdkId\":\"mongodb\",\"definitionBuildNumber\":\"null\",\"definitionTags\":[\"schema-free\",\"Database\",\"doubleActive\"],\"definitionPdkAPIVersion\":\"2.0.5-SNAPSHOT\",\"pdkType\":\"pdk\",\"pdkHash\":\"4335aaa005ec1a74a4e2166bded2962e939ad50239f48b023b884f35b54129a5\",\"capabilities\":[{\"type\":20,\"id\":\"source_incremental_update_event_have_before\"},{\"type\":11,\"id\":\"execute_command_function\"},{\"type\":11,\"id\":\"batch_read_function\"},{\"type\":11,\"id\":\"stream_read_function\"},{\"type\":11,\"id\":\"batch_count_function\"},{\"type\":11,\"id\":\"timestamp_to_stream_offset_function\"},{\"type\":11,\"id\":\"write_record_function\"},{\"type\":11,\"id\":\"query_by_advance_filter_function\"},{\"type\":11,\"id\":\"create_table_v2_function\"},{\"type\":11,\"id\":\"drop_table_function\"},{\"type\":11,\"id\":\"create_index_function\"},{\"type\":11,\"id\":\"query_indexes_function\"},{\"type\":11,\"id\":\"count_by_partition_filter_function\"},{\"type\":11,\"id\":\"get_read_partitions_function\"},{\"type\":11,\"id\":\"query_field_min_max_value_function\"},{\"type\":11,\"id\":\"transaction_begin_function\"},{\"type\":11,\"id\":\"transaction_commit_function\"},{\"type\":11,\"id\":\"transaction_rollback_function\"},{\"type\":11,\"id\":\"get_table_info_function\"},{\"type\":11,\"id\":\"get_table_names_function\"},{\"type\":11,\"id\":\"error_handle_function\"},{\"type\":20,\"id\":\"master_slave_merge\"},{\"type\":20,\"id\":\"dynamic_schema\"},{\"type\":20,\"id\":\"dml_insert_policy\",\"alternatives\":[\"update_on_exists\",\"ignore_on_exists\",\"just_insert\"]},{\"type\":20,\"id\":\"dml_update_policy\",\"alternatives\":[\"ignore_on_nonexists\",\"insert_on_nonexists\",\"log_on_nonexists\"]},{\"type\":20,\"id\":\"api_server_supported\"},{\"type\":20,\"id\":\"source_support_exactly_once\"}],\"retry\":0,\"everLoadSchema\":true,\"schemaVersion\":\"4f0fa5ba-4c7d-454d-b15b-e034d6556086\",\"status\":\"ready\",\"lastStatus\":\"ready\",\"tableCount\":2,\"testTime\":1768890124835,\"database_uri\":\"mongodb://null/null\",\"plain_password\":\"\",\"loadAllTables\":true,\"openTableExcludeFilter\":false,\"project\":\"\",\"transformed\":true,\"db_version\":\"8.0.9\",\"schema\":{},\"loadCount\":2,\"loadFieldsStatus\":\"finished\",\"submit\":true,\"loadSchemaField\":true,\"lastUpdate\":1768890124874,\"loadFieldErrMsg\":\"\",\"kafkaConsumerRequestTimeout\":0,\"kafkaConsumerUseTransactional\":false,\"kafkaMaxPollRecords\":0,\"kafkaPollTimeoutMS\":0,\"kafkaMaxFetchBytes\":0,\"kafkaMaxFetchWaitMS\":0,\"kafkaIgnoreInvalidRecord\":false,\"kafkaProducerRequestTimeout\":0,\"kafkaProducerUseTransactional\":false,\"kafkaRetries\":0,\"kafkaBatchSize\":0,\"kafkaAcks\":\"-1\",\"kafkaLingerMS\":0,\"kafkaDeliveryTimeoutMS\":0,\"kafkaMaxRequestSize\":0,\"kafkaMaxBlockMS\":0,\"kafkaBufferMemory\":0,\"kafkaCompressionType\":\"\",\"kafkaPartitionKey\":\"\",\"kafkaIgnorePushError\":false,\"agentTags\":[],\"shareCdcEnable\":false,\"accessNodeType\":\"AUTOMATIC_PLATFORM_ALLOCATION\",\"accessNodeProcessId\":\"\",\"accessNodeProcessIdList\":[],\"accessNodeTypeEmpty\":false,\"shareCDCExternalStorageId\":\"\",\"loadSchemaTime\":1768890125242,\"schemaUpdateHour\":\"default\",\"heartbeatEnable\":false,\"isInit\":false,\"alarmInfo\":\"DataSourceConnectionDto{name='MDM', connection_type='source_and_target', retry=0, status='ready', tableCount=2, loadAllTables=true, loadFieldsStatus=finished, loadFieldErrMsg=}\",\"createTime\":1768803675304,\"last_updated\":1768803675304}"},{"collectionName":"MetadataInstances","json":"{\"id\":\"69549865aedd5fe4733b3c1d\",\"lastUpdBy\":\"62bc5008d4958d013d97c7a6\",\"createUser\":\"admin@admin.com\",\"ancestorsName\":\"MDM\",\"hasPrimaryKey\":false,\"source\":{\"id\":\"695497a235a6fa171731395e\",\"_id\":\"695497a235a6fa171731395e\",\"user_id\":\"62bc5008d4958d013d97c7a6\",\"lastUpdBy\":\"62bc5008d4958d013d97c7a6\",\"createUser\":\"admin@admin.com\",\"name\":\"MDM\",\"connection_type\":\"source_and_target\",\"database_type\":\"MongoDB\",\"retry\":0,\"everLoadSchema\":true,\"schemaVersion\":\"4f0fa5ba-4c7d-454d-b15b-e034d6556086\",\"status\":\"ready\",\"tableCount\":2,\"testTime\":1768890124835,\"database_uri\":\"mongodb://null/null\",\"plain_password\":\"\",\"project\":\"\",\"transformed\":true,\"db_version\":\"8.0.9\",\"loadCount\":2,\"loadFieldsStatus\":\"finished\",\"submit\":true,\"loadSchemaField\":true,\"loadFieldErrMsg\":\"\",\"kafkaIgnoreInvalidRecord\":false,\"kafkaAcks\":\"-1\",\"kafkaCompressionType\":\"\",\"kafkaIgnorePushError\":false,\"agentTags\":[]},\"hasUnionIndex\":false,\"username\":\"admin@admin.com\",\"lastUpdate\":1768890124874,\"sourceType\":\"SOURCE\",\"hasTransformEx\":false,\"hasUpdateField\":false,\"createTime\":1768803675966,\"last_updated\":1768890125278,\"user_id\":\"62bc5008d4958d013d97c7a6\",\"qualified_name\":\"CONN_mongodb_io_tapdata_1_0-SNAPSHOT_695497a235a6fa171731395e\",\"meta_type\":\"database\",\"is_deleted\":false,\"original_name\":\"MDM\",\"dev_version\":1,\"last_user_name\":\"admin@admin.com\"}"},{"collectionName":"Connections","json":"{\"id\":\"695497a235a6fa171731395e\",\"name\":\"MDM\",\"config\":{\"mongodbLoadSchemaSampleSize\":1000,\"__connectionType\":\"source_and_target\",\"uri\":\"\",\"ssl\":false,\"schemaLimit\":1024,\"isUri\":true,\"id\":\"695497a235a6fa171731395e\"},\"connection_type\":\"source_and_target\",\"database_type\":\"MongoDB\",\"definitionScope\":\"public\",\"definitionVersion\":\"1.0-SNAPSHOT\",\"definitionGroup\":\"io.tapdata\",\"definitionPdkId\":\"mongodb\",\"definitionBuildNumber\":\"null\",\"definitionTags\":[\"schema-free\",\"Database\",\"doubleActive\"],\"definitionPdkAPIVersion\":\"2.0.5-SNAPSHOT\",\"pdkType\":\"pdk\",\"pdkHash\":\"4335aaa005ec1a74a4e2166bded2962e939ad50239f48b023b884f35b54129a5\",\"capabilities\":[{\"type\":20,\"id\":\"source_incremental_update_event_have_before\"},{\"type\":11,\"id\":\"execute_command_function\"},{\"type\":11,\"id\":\"batch_read_function\"},{\"type\":11,\"id\":\"stream_read_function\"},{\"type\":11,\"id\":\"batch_count_function\"},{\"type\":11,\"id\":\"timestamp_to_stream_offset_function\"},{\"type\":11,\"id\":\"write_record_function\"},{\"type\":11,\"id\":\"query_by_advance_filter_function\"},{\"type\":11,\"id\":\"create_table_v2_function\"},{\"type\":11,\"id\":\"drop_table_function\"},{\"type\":11,\"id\":\"create_index_function\"},{\"type\":11,\"id\":\"query_indexes_function\"},{\"type\":11,\"id\":\"count_by_partition_filter_function\"},{\"type\":11,\"id\":\"get_read_partitions_function\"},{\"type\":11,\"id\":\"query_field_min_max_value_function\"},{\"type\":11,\"id\":\"transaction_begin_function\"},{\"type\":11,\"id\":\"transaction_commit_function\"},{\"type\":11,\"id\":\"transaction_rollback_function\"},{\"type\":11,\"id\":\"get_table_info_function\"},{\"type\":11,\"id\":\"get_table_names_function\"},{\"type\":11,\"id\":\"error_handle_function\"},{\"type\":20,\"id\":\"master_slave_merge\"},{\"type\":20,\"id\":\"dynamic_schema\"},{\"type\":20,\"id\":\"dml_insert_policy\",\"alternatives\":[\"update_on_exists\",\"ignore_on_exists\",\"just_insert\"]},{\"type\":20,\"id\":\"dml_update_policy\",\"alternatives\":[\"ignore_on_nonexists\",\"insert_on_nonexists\",\"log_on_nonexists\"]},{\"type\":20,\"id\":\"api_server_supported\"},{\"type\":20,\"id\":\"source_support_exactly_once\"}],\"retry\":0,\"everLoadSchema\":true,\"schemaVersion\":\"4f0fa5ba-4c7d-454d-b15b-e034d6556086\",\"status\":\"ready\",\"lastStatus\":\"ready\",\"tableCount\":2,\"testTime\":1768890124835,\"database_uri\":\"mongodb://null/null\",\"plain_password\":\"\",\"loadAllTables\":true,\"openTableExcludeFilter\":false,\"project\":\"\",\"transformed\":true,\"db_version\":\"8.0.9\",\"schema\":{},\"loadCount\":2,\"loadFieldsStatus\":\"finished\",\"submit\":true,\"loadSchemaField\":true,\"lastUpdate\":1768890124874,\"loadFieldErrMsg\":\"\",\"kafkaConsumerRequestTimeout\":0,\"kafkaConsumerUseTransactional\":false,\"kafkaMaxPollRecords\":0,\"kafkaPollTimeoutMS\":0,\"kafkaMaxFetchBytes\":0,\"kafkaMaxFetchWaitMS\":0,\"kafkaIgnoreInvalidRecord\":false,\"kafkaProducerRequestTimeout\":0,\"kafkaProducerUseTransactional\":false,\"kafkaRetries\":0,\"kafkaBatchSize\":0,\"kafkaAcks\":\"-1\",\"kafkaLingerMS\":0,\"kafkaDeliveryTimeoutMS\":0,\"kafkaMaxRequestSize\":0,\"kafkaMaxBlockMS\":0,\"kafkaBufferMemory\":0,\"kafkaCompressionType\":\"\",\"kafkaPartitionKey\":\"\",\"kafkaIgnorePushError\":false,\"agentTags\":[],\"shareCdcEnable\":false,\"accessNodeType\":\"AUTOMATIC_PLATFORM_ALLOCATION\",\"accessNodeProcessId\":\"\",\"accessNodeProcessIdList\":[],\"accessNodeTypeEmpty\":false,\"shareCDCExternalStorageId\":\"\",\"loadSchemaTime\":1768890125242,\"schemaUpdateHour\":\"default\",\"heartbeatEnable\":false,\"isInit\":false,\"alarmInfo\":\"DataSourceConnectionDto{name='MDM', connection_type='source_and_target', retry=0, status='ready', tableCount=2, loadAllTables=true, loadFieldsStatus=finished, loadFieldErrMsg=}\",\"createTime\":1768803675304,\"last_updated\":1768803675304}"}]